nunchaku/__init__.py
nunchaku/_example_data.py
nunchaku/_models.py
nunchaku/gibbs_sampler.py
nunchaku/nunchaku.py
nunchaku-0.16.1.dist-info/METADATA
nunchaku-0.16.1.dist-info/WHEEL
nunchaku-0.16.1.dist-info/RECORD
