Metadata-Version: 2.3
Name: nunchaku
Version: 0.16.1
Summary: Optimally partitioning data into piece-wise linear segments.
License: MIT
Keywords: linear trend,Bayesian inference,log phase,exponential growth,change point analysis
Author: Yu Huo
Author-email: yhuo@tuta.io
Requires-Python: >=3.9,<3.13
Classifier: Intended Audience :: Science/Research
Classifier: License :: OSI Approved :: MIT License
Classifier: Operating System :: OS Independent
Classifier: Programming Language :: Python :: 3
Classifier: Programming Language :: Python :: 3.9
Classifier: Programming Language :: Python :: 3.10
Classifier: Programming Language :: Python :: 3.11
Classifier: Programming Language :: Python :: 3.12
Classifier: Topic :: Scientific/Engineering :: Bio-Informatics
Requires-Dist: matplotlib (>=3.5.0,<4.0.0)
Requires-Dist: numpy (>=2.0.0,<3.0.0)
Requires-Dist: pandas (>=1.4)
Requires-Dist: scipy (>=1.10.1,<2.0.0)
Requires-Dist: tqdm (>=4.65.0,<5.0.0)
Project-URL: Documentation, https://nunchaku.readthedocs.io
Project-URL: Homepage, https://nunchaku.readthedocs.io
Project-URL: Repository, https://git.ecdf.ed.ac.uk/s1856140/nunchaku
